kagurazaka/__init__.py
kagurazaka/main.py
kagurazaka/backbone/__init__.py
kagurazaka/backbone/mp.py
kagurazaka/backbone/torch_vanilla_single.py
kagurazaka/task/__init__.py
kagurazaka/task/normal.py
kagurazaka/task/torch_vanilla.py
kagurazaka/template/__init__.py
kagurazaka/template/io.py
kagurazaka/template/mixin.py
kagurazaka/template/task/__init__.py
kagurazaka/template/task/normal.py
kagurazaka/template/task/torch_vanilla.py
kagurazaka/utils/__init__.py
kagurazaka/utils/io.py
kagurazaka/utils/collate/__init__.py
kagurazaka/utils/collate/default_extended.py
kagurazaka-0.1.1.dist-info/METADATA
kagurazaka-0.1.1.dist-info/WHEEL
kagurazaka-0.1.1.dist-info/entry_points.txt
kagurazaka-0.1.1.dist-info/top_level.txt
kagurazaka-0.1.1.dist-info/RECORD
