Metadata-Version: 2.4
Name: kagurazaka
Version: 0.1.1
Summary: Dynamic distributed preprocessing task loader and dispatcher
Author: Haoyun Qin
Author-email: qhy.cis@gmail.com
Classifier: Programming Language :: Python :: 3
Classifier: License :: OSI Approved :: MIT License
Classifier: Operating System :: OS Independent
Requires-Python: >=3.6
Requires-Dist: tqdm
Requires-Dist: omegaconf
Dynamic: author
Dynamic: author-email
Dynamic: classifier
Dynamic: description
Dynamic: description-content-type
Dynamic: requires-dist
Dynamic: requires-python
Dynamic: summary
